Workbook
Name ChartValuesExtraPayment: AmortizationScheduleRaw!$A$2:INDEX(AmortizationScheduleRaw!$A:$A,AmortizationScheduleRaw!$K$2)
Name ChartValuesNoExtra: AmortizationScheduleNoExtraRaw!$A$2:INDEX(AmortizationScheduleNoExtraRaw!$A:$A,AmortizationScheduleNoExtraRaw!$K$2)
Name ExtraPayment: DashboardAndAssumptions!$C$8
Name InterestRate: DashboardAndAssumptions!$C$5
Name InterestSaved: DashboardAndAssumptions!$R$16
Name LoanAmount: DashboardAndAssumptions!$C$4
Name LoanTerm: DashboardAndAssumptions!$C$6
Name MonthlyPayment: DashboardAndAssumptions!$R$8
Name NumberOfMonths: DashboardAndAssumptions!$Q$12
Name NumberOfMonthsSaved: DashboardAndAssumptions!$Q$12
Name NumberOfMonthsSimplified: DashboardAndAssumptions!$Q$13
Name NumberOfPeriods: DashboardAndAssumptions!$R$12
Name PaymentFrequency: DashboardAndAssumptions!$C$7
Name PaymentsPerYear: DashboardAndAssumptions!$R$4
Name PaymentTitle: DashboardAndAssumptions!$Q$8
Name PayoffDate: DashboardAndAssumptions!$R$13
Name PeriodNumber: DashboardAndAssumptions!$R$12
Name StartDate: DashboardAndAssumptions!$C$9
Name TotalAmountPaid: DashboardAndAssumptions!$R$14
Name TotalExtraPayments: DashboardAndAssumptions!$R$15
Name TotalInterestPaid: DashboardAndAssumptions!$R$10
Name TotalLoan: DashboardAndAssumptions!$R$11
Name TotalPrincipal: DashboardAndAssumptions!$R$9

Sheet DashboardAndAssumptions
B4: Loan Amount | C4: 20000 | E4: Welcome to the Dynamic Loan Amortization and Prepayment Model. ← Please feel free to adjust the data in light blue. Note: all numbers are rounded to the second decimal point. The last total payment may vary from the constant scheduled total payment to accommodate rounding and any extra payments. | R4: =IF(C7="Weekly",52,IF(C7="Bi-Weekly",26,IF(C7="Monthly",12,IF(C7="Semi-Annually",2,IF(C7="Annually",1))))) -> 12
B5: Interest Rate (Annual) | C5: 0.06
B6: Loan Term (Years) | C6: 3
B7: Payments Frequency | C7: Monthly
B8: Extra Payment | C8: 0 | Q8: ="Scheduled " & PaymentFrequency & " Payment:" -> Scheduled Monthly Payment: | R8: =PMT(InterestRate/PaymentsPerYear, PaymentsPerYear*LoanTerm, -LoanAmount) + ExtraPayment -> 608.43875
B9: Start Date | C9: 46272 | R9: =-SUM(AmortizationScheduleRaw!G2:'AmortizationScheduleRaw'!G1561) -> 20000
R10: =-SUM(AmortizationScheduleRaw!E2:E1561) -> 1903.82
R11: =R9+R10 -> 21903.82
Q12: =IF(PaymentFrequency="Annually",((LoanTerm*PaymentsPerYear)-(NumberOfPeriods))*12, IF(PaymentFrequency="Semi-Annually",((LoanTerm*PaymentsPerYear)-(NumberOfPeriods))*6, IF(PaymentFrequency="Monthly",(LoanTerm*PaymentsPerYear)-(NumberOfPeriods), IF(PaymentFrequency="Bi-Weekly",((LoanTerm*PaymentsPerYear)-(NumberOfPeriods))/2, IF(PaymentFrequency="Weekly",((LoanTerm*PaymentsPerYear)-(NumberOfPeriods))/4))))) -> 0 | R12: =COUNTIF(AmortizationScheduleRaw!H:H,">0") + 1 -> 36
Q13: =IF(NumberOfMonths >= 12, ROUND(NumberOfMonths/12, 2) & " Year(s)", NumberOfMonths & " Month(s)") -> 0 Month(s) | R13: =IF(PaymentFrequency="Annually",EDATE(StartDate,NumberOfPeriods*12), IF(PaymentFrequency="Semi-Annually",EDATE(StartDate,NumberOfPeriods*6), IF(PaymentFrequency="Monthly",EDATE(StartDate,NumberOfPeriods), IF(PaymentFrequency="Bi-Weekly",StartDate+(NumberOfPeriods*14), IF(PaymentFrequency="Weekly",StartDate+(NumberOfPeriods*7)))))) -> 47368
R14: =-SUM(AmortizationScheduleRaw!C:C) -> 21903.82
R15: =-SUM(AmortizationScheduleRaw!D2:D1561) -> 0
R16: =-SUM(AmortizationScheduleNoExtraRaw!E2:E1561) + SUM(AmortizationScheduleRaw!E2:E1561) -> 0

Sheet AmortizationSchedule
A1: ="Period (" & PaymentFrequency & ")" -> Period (Monthly) | B1: Beginning Balance | C1: Total Payment | D1: Extra Payment | E1: Interest | F1: Principal | G1: Total Principal | H1: Ending Balance
A2: {=_xlfn._xlws.FILTER(AmortizationScheduleRaw!A2:H1561, AmortizationScheduleRaw!B2:B1561 > 0,"")} -> 1 | B2: 20000 | C2: -608.44 | D2: 0 | E2: -100 | F2: -508.44 | G2: -508.44 | H2: 19491.56
A3: 2 | B3: 19491.56 | C3: -608.44 | D3: 0 | E3: -97.46 | F3: -510.98 | G3: -510.98 | H3: 18980.58
A4: 3 | B4: 18980.58 | C4: -608.44 | D4: 0 | E4: -94.9 | F4: -513.54 | G4: -513.54 | H4: 18467.04
A5: 4 | B5: 18467.04 | C5: -608.44 | D5: 0 | E5: -92.34 | F5: -516.1 | G5: -516.1 | H5: 17950.94
A6: 5 | B6: 17950.94 | C6: -608.44 | D6: 0 | E6: -89.75 | F6: -518.69 | G6: -518.69 | H6: 17432.25
A7: 6 | B7: 17432.25 | C7: -608.44 | D7: 0 | E7: -87.16 | F7: -521.28 | G7: -521.28 | H7: 16910.97
A8: 7 | B8: 16910.97 | C8: -608.44 | D8: 0 | E8: -84.55 | F8: -523.89 | G8: -523.89 | H8: 16387.08
A9: 8 | B9: 16387.08 | C9: -608.44 | D9: 0 | E9: -81.94 | F9: -526.5 | G9: -526.5 | H9: 15860.58
A10: 9 | B10: 15860.58 | C10: -608.44 | D10: 0 | E10: -79.3 | F10: -529.14 | G10: -529.14 | H10: 15331.44
A11: 10 | B11: 15331.44 | C11: -608.44 | D11: 0 | E11: -76.66 | F11: -531.78 | G11: -531.78 | H11: 14799.66
A12: 11 | B12: 14799.66 | C12: -608.44 | D12: 0 | E12: -74 | F12: -534.44 | G12: -534.44 | H12: 14265.22
A13: 12 | B13: 14265.22 | C13: -608.44 | D13: 0 | E13: -71.33 | F13: -537.11 | G13: -537.11 | H13: 13728.11
A14: 13 | B14: 13728.11 | C14: -608.44 | D14: 0 | E14: -68.64 | F14: -539.8 | G14: -539.8 | H14: 13188.31
... A37: 36 | B37: 605.39 | C37: -608.42 | D37: 0 | E37: -3.03 | F37: -605.39 | G37: -605.39 | H37: 0

Sheet AmortizationScheduleRaw
A1: ="Period (" & PaymentFrequency & ")" -> Period (Monthly) | B1: Beginning Balance | C1: Total Payment | D1: Extra Payment | E1: Interest | F1: Principal | G1: Total Principal | H1: Ending Balance
A2: {=_xlfn.SEQUENCE(1560)} -> 1 | B2: =LoanAmount -> 20000 | C2: =IF($B2<=0, 0, $D2+$E2+$F2) -> -608.44 | D2: =IF(ExtraPayment=0, 0, IF(AND($B2<>0,ExtraPayment<=LoanAmount),-ExtraPayment,-($F2)-$B2)) -> 0 | E2: =IF($B2 <= 0, 0, -ROUND($B2 * (InterestRate / PaymentsPerYear), 2)) -> -100 | F2: =ROUND(IFERROR(IF(OR($B2 <=0, $B2 = ExtraPayment),0, MAX(-$B2, -(-PMT(InterestRate/PaymentsPerYear,LoanTerm*PaymentsPerYear,LoanAmount) + $E2))), 0), 2) -> -508.44 | G2: =$D2+$F2 -> -508.44 | H2: =ROUND(IF($B2 <= 0, 0, MAX(0, $B2 + $G2)), 2) -> 19491.56 | K2: =COUNTIF(AmortizationScheduleRaw!H:H,">0") + 1 -> 36
A3: 2 | B3: =ROUND(IF($H2 >= 0, MAX($H2, $F2), 0), 2) -> 19491.56 | C3: =IF($B3 <= 0, 0, $D3+$E3+$F3) -> -608.44 | D3: =IF(ExtraPayment=0, 0, IF(AND($B3<>0,ExtraPayment<=$B3),-ExtraPayment,-($F3)-$B3)) -> 0 | E3: =IF($B3 <= 0, 0, -ROUND($B3 * (InterestRate / PaymentsPerYear), 2)) -> -97.46 | F3: =ROUND(IFERROR(IF(OR($B3 <=0, $B3 = ExtraPayment),0, MAX(-$B3, -(-PMT(InterestRate/PaymentsPerYear,LoanTerm*PaymentsPerYear,LoanAmount) + $E3))), 0), 2) -> -510.98 | G3: =$D3+$F3 -> -510.98 | H3: =ROUND(IF($B3 <= 0, 0,MAX(0, $B3 + $G3)), 2) -> 18980.58
A4: 3 | B4: =ROUND(IF($H3 >= 0, MAX($H3, $F3), 0), 2) -> 18980.58 | C4: =IF($B4 <= 0, 0, $D4+$E4+$F4) -> -608.44 | D4: =IF(ExtraPayment=0, 0, IF(AND($B4<>0,ExtraPayment<=$B4),-ExtraPayment,-($F4)-$B4)) -> 0 | E4: =IF($B4 <= 0, 0, -ROUND($B4 * (InterestRate / PaymentsPerYear), 2)) -> -94.9 | F4: =ROUND(IFERROR(IF(OR($B4 <=0, $B4 = ExtraPayment),0, MAX(-$B4, -(-PMT(InterestRate/PaymentsPerYear,LoanTerm*PaymentsPerYear,LoanAmount) + $E4))), 0), 2) -> -513.54 | G4: =$D4+$F4 -> -513.54 | H4: =ROUND(IF($B4 <= 0, 0,MAX(0, $B4 + $G4)), 2) -> 18467.04
A5: 4 | B5: =ROUND(IF($H4 >= 0, MAX($H4, $F4), 0), 2) -> 18467.04 | C5: =IF($B5 <= 0, 0, $D5+$E5+$F5) -> -608.44 | D5: =IF(ExtraPayment=0, 0, IF(AND($B5<>0,ExtraPayment<=$B5),-ExtraPayment,-($F5)-$B5)) -> 0 | E5: =IF($B5 <= 0, 0, -ROUND($B5 * (InterestRate / PaymentsPerYear), 2)) -> -92.34 | F5: =ROUND(IFERROR(IF(OR($B5 <=0, $B5 = ExtraPayment),0, MAX(-$B5, -(-PMT(InterestRate/PaymentsPerYear,LoanTerm*PaymentsPerYear,LoanAmount) + $E5))), 0), 2) -> -516.1 | G5: =$D5+$F5 -> -516.1 | H5: =ROUND(IF($B5 <= 0, 0,MAX(0, $B5 + $G5)), 2) -> 17950.94
A6: 5 | B6: =ROUND(IF($H5 >= 0, MAX($H5, $F5), 0), 2) -> 17950.94 | C6: =IF($B6 <= 0, 0, $D6+$E6+$F6) -> -608.44 | D6: =IF(ExtraPayment=0, 0, IF(AND($B6<>0,ExtraPayment<=$B6),-ExtraPayment,-($F6)-$B6)) -> 0 | E6: =IF($B6 <= 0, 0, -ROUND($B6 * (InterestRate / PaymentsPerYear), 2)) -> -89.75 | F6: =ROUND(IFERROR(IF(OR($B6 <=0, $B6 = ExtraPayment),0, MAX(-$B6, -(-PMT(InterestRate/PaymentsPerYear,LoanTerm*PaymentsPerYear,LoanAmount) + $E6))), 0), 2) -> -518.69 | G6: =$D6+$F6 -> -518.69 | H6: =ROUND(IF($B6 <= 0, 0,MAX(0, $B6 + $G6)), 2) -> 17432.25
A7: 6 | B7: =ROUND(IF($H6 >= 0, MAX($H6, $F6), 0), 2) -> 17432.25 | C7: =IF($B7 <= 0, 0, $D7+$E7+$F7) -> -608.44 | D7: =IF(ExtraPayment=0, 0, IF(AND($B7<>0,ExtraPayment<=$B7),-ExtraPayment,-($F7)-$B7)) -> 0 | E7: =IF($B7 <= 0, 0, -ROUND($B7 * (InterestRate / PaymentsPerYear), 2)) -> -87.16 | F7: =ROUND(IFERROR(IF(OR($B7 <=0, $B7 = ExtraPayment),0, MAX(-$B7, -(-PMT(InterestRate/PaymentsPerYear,LoanTerm*PaymentsPerYear,LoanAmount) + $E7))), 0), 2) -> -521.28 | G7: =$D7+$F7 -> -521.28 | H7: =ROUND(IF($B7 <= 0, 0,MAX(0, $B7 + $G7)), 2) -> 16910.97
A8: 7 | B8: =ROUND(IF($H7 >= 0, MAX($H7, $F7), 0), 2) -> 16910.97 | C8: =IF($B8 <= 0, 0, $D8+$E8+$F8) -> -608.44 | D8: =IF(ExtraPayment=0, 0, IF(AND($B8<>0,ExtraPayment<=$B8),-ExtraPayment,-($F8)-$B8)) -> 0 | E8: =IF($B8 <= 0, 0, -ROUND($B8 * (InterestRate / PaymentsPerYear), 2)) -> -84.55 | F8: =ROUND(IFERROR(IF(OR($B8 <=0, $B8 = ExtraPayment),0, MAX(-$B8, -(-PMT(InterestRate/PaymentsPerYear,LoanTerm*PaymentsPerYear,LoanAmount) + $E8))), 0), 2) -> -523.89 | G8: =$D8+$F8 -> -523.89 | H8: =ROUND(IF($B8 <= 0, 0,MAX(0, $B8 + $G8)), 2) -> 16387.08
A9: 8 | B9: =ROUND(IF($H8 >= 0, MAX($H8, $F8), 0), 2) -> 16387.08 | C9: =IF($B9 <= 0, 0, $D9+$E9+$F9) -> -608.44 | D9: =IF(ExtraPayment=0, 0, IF(AND($B9<>0,ExtraPayment<=$B9),-ExtraPayment,-($F9)-$B9)) -> 0 | E9: =IF($B9 <= 0, 0, -ROUND($B9 * (InterestRate / PaymentsPerYear), 2)) -> -81.94 | F9: =ROUND(IFERROR(IF(OR($B9 <=0, $B9 = ExtraPayment),0, MAX(-$B9, -(-PMT(InterestRate/PaymentsPerYear,LoanTerm*PaymentsPerYear,LoanAmount) + $E9))), 0), 2) -> -526.5 | G9: =$D9+$F9 -> -526.5 | H9: =ROUND(IF($B9 <= 0, 0,MAX(0, $B9 + $G9)), 2) -> 15860.58
A10: 9 | B10: =ROUND(IF($H9 >= 0, MAX($H9, $F9), 0), 2) -> 15860.58 | C10: =IF($B10 <= 0, 0, $D10+$E10+$F10) -> -608.44 | D10: =IF(ExtraPayment=0, 0, IF(AND($B10<>0,ExtraPayment<=$B10),-ExtraPayment,-($F10)-$B10)) -> 0 | E10: =IF($B10 <= 0, 0, -ROUND($B10 * (InterestRate / PaymentsPerYear), 2)) -> -79.3 | F10: =ROUND(IFERROR(IF(OR($B10 <=0, $B10 = ExtraPayment),0, MAX(-$B10, -(-PMT(InterestRate/PaymentsPerYear,LoanTerm*PaymentsPerYear,LoanAmount) + $E10))), 0), 2) -> -529.14 | G10: =$D10+$F10 -> -529.14 | H10: =ROUND(IF($B10 <= 0, 0,MAX(0, $B10 + $G10)), 2) -> 15331.44
A11: 10 | B11: =ROUND(IF($H10 >= 0, MAX($H10, $F10), 0), 2) -> 15331.44 | C11: =IF($B11 <= 0, 0, $D11+$E11+$F11) -> -608.44 | D11: =IF(ExtraPayment=0, 0, IF(AND($B11<>0,ExtraPayment<=$B11),-ExtraPayment,-($F11)-$B11)) -> 0 | E11: =IF($B11 <= 0, 0, -ROUND($B11 * (InterestRate / PaymentsPerYear), 2)) -> -76.66 | F11: =ROUND(IFERROR(IF(OR($B11 <=0, $B11 = ExtraPayment),0, MAX(-$B11, -(-PMT(InterestRate/PaymentsPerYear,LoanTerm*PaymentsPerYear,LoanAmount) + $E11))), 0), 2) -> -531.78 | G11: =$D11+$F11 -> -531.78 | H11: =ROUND(IF($B11 <= 0, 0,MAX(0, $B11 + $G11)), 2) -> 14799.66
A12: 11 | B12: =ROUND(IF($H11 >= 0, MAX($H11, $F11), 0), 2) -> 14799.66 | C12: =IF($B12 <= 0, 0, $D12+$E12+$F12) -> -608.44 | D12: =IF(ExtraPayment=0, 0, IF(AND($B12<>0,ExtraPayment<=$B12),-ExtraPayment,-($F12)-$B12)) -> 0 | E12: =IF($B12 <= 0, 0, -ROUND($B12 * (InterestRate / PaymentsPerYear), 2)) -> -74 | F12: =ROUND(IFERROR(IF(OR($B12 <=0, $B12 = ExtraPayment),0, MAX(-$B12, -(-PMT(InterestRate/PaymentsPerYear,LoanTerm*PaymentsPerYear,LoanAmount) + $E12))), 0), 2) -> -534.44 | G12: =$D12+$F12 -> -534.44 | H12: =ROUND(IF($B12 <= 0, 0,MAX(0, $B12 + $G12)), 2) -> 14265.22
A13: 12 | B13: =ROUND(IF($H12 >= 0, MAX($H12, $F12), 0), 2) -> 14265.22 | C13: =IF($B13 <= 0, 0, $D13+$E13+$F13) -> -608.44 | D13: =IF(ExtraPayment=0, 0, IF(AND($B13<>0,ExtraPayment<=$B13),-ExtraPayment,-($F13)-$B13)) -> 0 | E13: =IF($B13 <= 0, 0, -ROUND($B13 * (InterestRate / PaymentsPerYear), 2)) -> -71.33 | F13: =ROUND(IFERROR(IF(OR($B13 <=0, $B13 = ExtraPayment),0, MAX(-$B13, -(-PMT(InterestRate/PaymentsPerYear,LoanTerm*PaymentsPerYear,LoanAmount) + $E13))), 0), 2) -> -537.11 | G13: =$D13+$F13 -> -537.11 | H13: =ROUND(IF($B13 <= 0, 0,MAX(0, $B13 + $G13)), 2) -> 13728.11
A14: 13 | B14: =ROUND(IF($H13 >= 0, MAX($H13, $F13), 0), 2) -> 13728.11 | C14: =IF($B14 <= 0, 0, $D14+$E14+$F14) -> -608.44 | D14: =IF(ExtraPayment=0, 0, IF(AND($B14<>0,ExtraPayment<=$B14),-ExtraPayment,-($F14)-$B14)) -> 0 | E14: =IF($B14 <= 0, 0, -ROUND($B14 * (InterestRate / PaymentsPerYear), 2)) -> -68.64 | F14: =ROUND(IFERROR(IF(OR($B14 <=0, $B14 = ExtraPayment),0, MAX(-$B14, -(-PMT(InterestRate/PaymentsPerYear,LoanTerm*PaymentsPerYear,LoanAmount) + $E14))), 0), 2) -> -539.8 | G14: =$D14+$F14 -> -539.8 | H14: =ROUND(IF($B14 <= 0, 0,MAX(0, $B14 + $G14)), 2) -> 13188.31
... A1561: 1560 | B1561: =ROUND(IF($H1560 >= 0, MAX($H1560, $F1560), 0), 2) -> 0 | C1561: =IF($B1561 <= 0, 0, $D1561+$E1561+$F1561) -> 0 | D1561: =IF(ExtraPayment=0, 0, IF(AND($B1561<>0,ExtraPayment<=$B1561),-ExtraPayment,-($F1561)-$B1561)) -> 0 | E1561: =IF($B1561 <= 0, 0, -ROUND($B1561 * (InterestRate / PaymentsPerYear), 2)) -> 0 | F1561: =ROUND(IFERROR(IF(OR($B1561 <=0, $B1561 = ExtraPayment),0, MAX(-$B1561, -(-PMT(InterestRate/PaymentsPerYear,LoanTerm*PaymentsPerYear,LoanAmount) + $E1561))), 0), 2) -> 0 | G1561: =$D1561+$F1561 -> 0 | H1561: =ROUND(IF($B1561 <= 0, 0,MAX(0, $B1561 + $G1561)), 2) -> 0

Sheet AmortizationScheduleNoExtra
A1: ="Period (" & PaymentFrequency & ")" -> Period (Monthly) | B1: Beginning Balance | C1: Total Payment | D1: Extra Payment | E1: Interest | F1: Principal | G1: Total Principal | H1: Ending Balance
A2: {=_xlfn._xlws.FILTER(AmortizationScheduleNoExtraRaw!A2:H1561, AmortizationScheduleNoExtraRaw!B2:B1561 > 0,"")} -> 1 | B2: 20000 | C2: -608.44 | D2: 0 | E2: -100 | F2: -508.44 | G2: -508.44 | H2: 19491.56
A3: 2 | B3: 19491.56 | C3: -608.44 | D3: 0 | E3: -97.46 | F3: -510.98 | G3: -510.98 | H3: 18980.58
A4: 3 | B4: 18980.58 | C4: -608.44 | D4: 0 | E4: -94.9 | F4: -513.54 | G4: -513.54 | H4: 18467.04
A5: 4 | B5: 18467.04 | C5: -608.44 | D5: 0 | E5: -92.34 | F5: -516.1 | G5: -516.1 | H5: 17950.94
A6: 5 | B6: 17950.94 | C6: -608.44 | D6: 0 | E6: -89.75 | F6: -518.69 | G6: -518.69 | H6: 17432.25
A7: 6 | B7: 17432.25 | C7: -608.44 | D7: 0 | E7: -87.16 | F7: -521.28 | G7: -521.28 | H7: 16910.97
A8: 7 | B8: 16910.97 | C8: -608.44 | D8: 0 | E8: -84.55 | F8: -523.89 | G8: -523.89 | H8: 16387.08
A9: 8 | B9: 16387.08 | C9: -608.44 | D9: 0 | E9: -81.94 | F9: -526.5 | G9: -526.5 | H9: 15860.58
A10: 9 | B10: 15860.58 | C10: -608.44 | D10: 0 | E10: -79.3 | F10: -529.14 | G10: -529.14 | H10: 15331.44
A11: 10 | B11: 15331.44 | C11: -608.44 | D11: 0 | E11: -76.66 | F11: -531.78 | G11: -531.78 | H11: 14799.66
A12: 11 | B12: 14799.66 | C12: -608.44 | D12: 0 | E12: -74 | F12: -534.44 | G12: -534.44 | H12: 14265.22
A13: 12 | B13: 14265.22 | C13: -608.44 | D13: 0 | E13: -71.33 | F13: -537.11 | G13: -537.11 | H13: 13728.11
A14: 13 | B14: 13728.11 | C14: -608.44 | D14: 0 | E14: -68.64 | F14: -539.8 | G14: -539.8 | H14: 13188.31
... A37: 36 | B37: 605.39 | C37: -608.42 | D37: 0 | E37: -3.03 | F37: -605.39 | G37: -605.39 | H37: 0

Sheet AmortizationScheduleNoExtraRaw
A1: ="Period (" & PaymentFrequency & ")" -> Period (Monthly) | B1: Beginning Balance | C1: Total Payment | D1: Extra Payment | E1: Interest | F1: Principal | G1: Total Principal | H1: Ending Balance
A2: {=_xlfn.SEQUENCE(1560)} -> 1 | B2: =LoanAmount -> 20000 | C2: =IF($B2<=0, 0, $E2+$F2) -> -608.44 | E2: =IF($B2 <= 0, 0, -ROUND($B2 * (InterestRate / PaymentsPerYear), 2)) -> -100 | F2: =ROUND(IFERROR(IF($B2<=0,0, MAX(-$B2, -(-PMT(InterestRate/PaymentsPerYear,LoanTerm*PaymentsPerYear,LoanAmount) + $E2))), 0), 2) -> -508.44 | G2: =$F2 -> -508.44 | H2: =ROUND(IF($B2 <= 0, 0, MAX(0, $B2 + $G2)), 2) -> 19491.56
A3: 2 | B3: =ROUND(IF($H2 >= 0, MAX($H2, $F2), 0), 2) -> 19491.56 | C3: =IF($B3 <= 0, 0, $E3+$F3) -> -608.44 | E3: =IF($B3 <= 0, 0, -ROUND($B3 * (InterestRate / PaymentsPerYear), 2)) -> -97.46 | F3: =ROUND(IFERROR(IF($B3<=0,0, MAX(-$B3, -(-PMT(InterestRate/PaymentsPerYear,LoanTerm*PaymentsPerYear,LoanAmount) + $E3))), 0), 2) -> -510.98 | G3: =$F3 -> -510.98 | H3: =ROUND(IF($B3 <= 0, 0,MAX(0, $B3 + $G3)), 2) -> 18980.58
A4: 3 | B4: =ROUND(IF($H3 >= 0, MAX($H3, $F3), 0), 2) -> 18980.58 | C4: =IF($B4 <= 0, 0, $E4+$F4) -> -608.44 | E4: =IF($B4 <= 0, 0, -ROUND($B4 * (InterestRate / PaymentsPerYear), 2)) -> -94.9 | F4: =ROUND(IFERROR(IF($B4<=0,0, MAX(-$B4, -(-PMT(InterestRate/PaymentsPerYear,LoanTerm*PaymentsPerYear,LoanAmount) + $E4))), 0), 2) -> -513.54 | G4: =$F4 -> -513.54 | H4: =ROUND(IF($B4 <= 0, 0,MAX(0, $B4 + $G4)), 2) -> 18467.04
A5: 4 | B5: =ROUND(IF($H4 >= 0, MAX($H4, $F4), 0), 2) -> 18467.04 | C5: =IF($B5 <= 0, 0, $E5+$F5) -> -608.44 | E5: =IF($B5 <= 0, 0, -ROUND($B5 * (InterestRate / PaymentsPerYear), 2)) -> -92.34 | F5: =ROUND(IFERROR(IF($B5<=0,0, MAX(-$B5, -(-PMT(InterestRate/PaymentsPerYear,LoanTerm*PaymentsPerYear,LoanAmount) + $E5))), 0), 2) -> -516.1 | G5: =$F5 -> -516.1 | H5: =ROUND(IF($B5 <= 0, 0,MAX(0, $B5 + $G5)), 2) -> 17950.94
A6: 5 | B6: =ROUND(IF($H5 >= 0, MAX($H5, $F5), 0), 2) -> 17950.94 | C6: =IF($B6 <= 0, 0, $E6+$F6) -> -608.44 | E6: =IF($B6 <= 0, 0, -ROUND($B6 * (InterestRate / PaymentsPerYear), 2)) -> -89.75 | F6: =ROUND(IFERROR(IF($B6<=0,0, MAX(-$B6, -(-PMT(InterestRate/PaymentsPerYear,LoanTerm*PaymentsPerYear,LoanAmount) + $E6))), 0), 2) -> -518.69 | G6: =$F6 -> -518.69 | H6: =ROUND(IF($B6 <= 0, 0,MAX(0, $B6 + $G6)), 2) -> 17432.25
A7: 6 | B7: =ROUND(IF($H6 >= 0, MAX($H6, $F6), 0), 2) -> 17432.25 | C7: =IF($B7 <= 0, 0, $E7+$F7) -> -608.44 | E7: =IF($B7 <= 0, 0, -ROUND($B7 * (InterestRate / PaymentsPerYear), 2)) -> -87.16 | F7: =ROUND(IFERROR(IF($B7<=0,0, MAX(-$B7, -(-PMT(InterestRate/PaymentsPerYear,LoanTerm*PaymentsPerYear,LoanAmount) + $E7))), 0), 2) -> -521.28 | G7: =$F7 -> -521.28 | H7: =ROUND(IF($B7 <= 0, 0,MAX(0, $B7 + $G7)), 2) -> 16910.97
A8: 7 | B8: =ROUND(IF($H7 >= 0, MAX($H7, $F7), 0), 2) -> 16910.97 | C8: =IF($B8 <= 0, 0, $E8+$F8) -> -608.44 | E8: =IF($B8 <= 0, 0, -ROUND($B8 * (InterestRate / PaymentsPerYear), 2)) -> -84.55 | F8: =ROUND(IFERROR(IF($B8<=0,0, MAX(-$B8, -(-PMT(InterestRate/PaymentsPerYear,LoanTerm*PaymentsPerYear,LoanAmount) + $E8))), 0), 2) -> -523.89 | G8: =$F8 -> -523.89 | H8: =ROUND(IF($B8 <= 0, 0,MAX(0, $B8 + $G8)), 2) -> 16387.08
A9: 8 | B9: =ROUND(IF($H8 >= 0, MAX($H8, $F8), 0), 2) -> 16387.08 | C9: =IF($B9 <= 0, 0, $E9+$F9) -> -608.44 | E9: =IF($B9 <= 0, 0, -ROUND($B9 * (InterestRate / PaymentsPerYear), 2)) -> -81.94 | F9: =ROUND(IFERROR(IF($B9<=0,0, MAX(-$B9, -(-PMT(InterestRate/PaymentsPerYear,LoanTerm*PaymentsPerYear,LoanAmount) + $E9))), 0), 2) -> -526.5 | G9: =$F9 -> -526.5 | H9: =ROUND(IF($B9 <= 0, 0,MAX(0, $B9 + $G9)), 2) -> 15860.58
A10: 9 | B10: =ROUND(IF($H9 >= 0, MAX($H9, $F9), 0), 2) -> 15860.58 | C10: =IF($B10 <= 0, 0, $E10+$F10) -> -608.44 | E10: =IF($B10 <= 0, 0, -ROUND($B10 * (InterestRate / PaymentsPerYear), 2)) -> -79.3 | F10: =ROUND(IFERROR(IF($B10<=0,0, MAX(-$B10, -(-PMT(InterestRate/PaymentsPerYear,LoanTerm*PaymentsPerYear,LoanAmount) + $E10))), 0), 2) -> -529.14 | G10: =$F10 -> -529.14 | H10: =ROUND(IF($B10 <= 0, 0,MAX(0, $B10 + $G10)), 2) -> 15331.44
A11: 10 | B11: =ROUND(IF($H10 >= 0, MAX($H10, $F10), 0), 2) -> 15331.44 | C11: =IF($B11 <= 0, 0, $E11+$F11) -> -608.44 | E11: =IF($B11 <= 0, 0, -ROUND($B11 * (InterestRate / PaymentsPerYear), 2)) -> -76.66 | F11: =ROUND(IFERROR(IF($B11<=0,0, MAX(-$B11, -(-PMT(InterestRate/PaymentsPerYear,LoanTerm*PaymentsPerYear,LoanAmount) + $E11))), 0), 2) -> -531.78 | G11: =$F11 -> -531.78 | H11: =ROUND(IF($B11 <= 0, 0,MAX(0, $B11 + $G11)), 2) -> 14799.66
A12: 11 | B12: =ROUND(IF($H11 >= 0, MAX($H11, $F11), 0), 2) -> 14799.66 | C12: =IF($B12 <= 0, 0, $E12+$F12) -> -608.44 | E12: =IF($B12 <= 0, 0, -ROUND($B12 * (InterestRate / PaymentsPerYear), 2)) -> -74 | F12: =ROUND(IFERROR(IF($B12<=0,0, MAX(-$B12, -(-PMT(InterestRate/PaymentsPerYear,LoanTerm*PaymentsPerYear,LoanAmount) + $E12))), 0), 2) -> -534.44 | G12: =$F12 -> -534.44 | H12: =ROUND(IF($B12 <= 0, 0,MAX(0, $B12 + $G12)), 2) -> 14265.22
A13: 12 | B13: =ROUND(IF($H12 >= 0, MAX($H12, $F12), 0), 2) -> 14265.22 | C13: =IF($B13 <= 0, 0, $E13+$F13) -> -608.44 | E13: =IF($B13 <= 0, 0, -ROUND($B13 * (InterestRate / PaymentsPerYear), 2)) -> -71.33 | F13: =ROUND(IFERROR(IF($B13<=0,0, MAX(-$B13, -(-PMT(InterestRate/PaymentsPerYear,LoanTerm*PaymentsPerYear,LoanAmount) + $E13))), 0), 2) -> -537.11 | G13: =$F13 -> -537.11 | H13: =ROUND(IF($B13 <= 0, 0,MAX(0, $B13 + $G13)), 2) -> 13728.11
A14: 13 | B14: =ROUND(IF($H13 >= 0, MAX($H13, $F13), 0), 2) -> 13728.11 | C14: =IF($B14 <= 0, 0, $E14+$F14) -> -608.44 | E14: =IF($B14 <= 0, 0, -ROUND($B14 * (InterestRate / PaymentsPerYear), 2)) -> -68.64 | F14: =ROUND(IFERROR(IF($B14<=0,0, MAX(-$B14, -(-PMT(InterestRate/PaymentsPerYear,LoanTerm*PaymentsPerYear,LoanAmount) + $E14))), 0), 2) -> -539.8 | G14: =$F14 -> -539.8 | H14: =ROUND(IF($B14 <= 0, 0,MAX(0, $B14 + $G14)), 2) -> 13188.31
... A1561: 1560 | B1561: =ROUND(IF($H1560 >= 0, MAX($H1560, $F1560), 0), 2) -> 0 | C1561: =IF($B1561 <= 0, 0, $E1561+$F1561) -> 0 | E1561: =IF($B1561 <= 0, 0, -ROUND($B1561 * (InterestRate / PaymentsPerYear), 2)) -> 0 | F1561: =ROUND(IFERROR(IF($B1561<=0,0, MAX(-$B1561, -(-PMT(InterestRate/PaymentsPerYear,LoanTerm*PaymentsPerYear,LoanAmount) + $E1561))), 0), 2) -> 0 | G1561: =$F1561 -> 0 | H1561: =ROUND(IF($B1561 <= 0, 0,MAX(0, $B1561 + $G1561)), 2) -> 0
